vasp_step/__init__.py
vasp_step/_version.py
vasp_step/energy.py
vasp_step/energy_parameters.py
vasp_step/energy_step.py
vasp_step/metadata.py
vasp_step/tk_energy.py
vasp_step/tk_vasp.py
vasp_step/vasp.py
vasp_step/vasp_step.py
vasp_step/data/properties.csv
vasp_step/data/references.bib
vasp_step-2025.10.22.dist-info/licenses/AUTHORS.rst
vasp_step-2025.10.22.dist-info/licenses/LICENSE
vasp_step-2025.10.22.dist-info/METADATA
vasp_step-2025.10.22.dist-info/WHEEL
vasp_step-2025.10.22.dist-info/entry_points.txt
vasp_step-2025.10.22.dist-info/top_level.txt
vasp_step-2025.10.22.dist-info/zip-safe
vasp_step-2025.10.22.dist-info/RECORD
