Metadata-Version: 2.4
Name: vasp_step
Version: 2025.10.22
Summary: A SEAMM plug-in for VASP
Home-page: https://github.com/molssi-seamm/vasp_step
Author: Paul Saxe
Author-email: psaxe@molssi.org
License: BSD-3-Clause
Keywords: SEAMM,SEAMMplugin,flowchart
Platform: Linux
Platform: Mac OS-X
Platform: Unix
Platform: Windows
Classifier: Environment :: Plugins
Classifier: Development Status :: 2 - Pre-Alpha
Classifier: Intended Audience :: Science/Research
Classifier: Topic :: Scientific/Engineering :: Chemistry
Classifier: Topic :: Scientific/Engineering :: Physics
Classifier: License :: OSI Approved :: BSD License
Classifier: Natural Language :: English
Classifier: Programming Language :: Python :: 3 :: Only
Classifier: Programming Language :: Python :: 3.8
Classifier: Programming Language :: Python :: 3.9
License-File: LICENSE
License-File: AUTHORS.rst
Requires-Dist: h5py
Requires-Dist: py-cpuinfo
Requires-Dist: seamm
Requires-Dist: seamm-util
Requires-Dist: seamm-widgets
Requires-Dist: tabulate
Dynamic: author
Dynamic: author-email
Dynamic: classifier
Dynamic: description
Dynamic: description-content-type
Dynamic: home-page
Dynamic: keywords
Dynamic: license
Dynamic: license-file
Dynamic: platform
Dynamic: requires-dist
Dynamic: summary
